sckit/__init__.py
sckit/pg.py
sckit-0.0.5.data/scripts/pg.py
sckit-0.0.5.dist-info/METADATA
sckit-0.0.5.dist-info/WHEEL
sckit-0.0.5.dist-info/top_level.txt
sckit-0.0.5.dist-info/RECORD
